OpenDiscovery/.DS_Store
OpenDiscovery/Vina.py
OpenDiscovery/__init__.py
OpenDiscovery/runProcess.py
OpenDiscovery/screen.py
OpenDiscovery/helpers/.DS_Store
OpenDiscovery/helpers/__init__.py
OpenDiscovery/helpers/log.py
OpenDiscovery/lib/extract.awk
OpenDiscovery/lib/prepare_ligand4.py
OpenDiscovery/lib/pythonsh
OpenDiscovery/lib/vina-linux/vina
OpenDiscovery/lib/vina-osx/vina
OpenDiscovery/md/__init__.py
OpenDiscovery/md/prepare.py
OpenDiscovery-2.5.data/scripts/odscreen
OpenDiscovery-2.5.dist-info/DESCRIPTION.rst
OpenDiscovery-2.5.dist-info/METADATA
OpenDiscovery-2.5.dist-info/RECORD
OpenDiscovery-2.5.dist-info/WHEEL
OpenDiscovery-2.5.dist-info/metadata.json
OpenDiscovery-2.5.dist-info/pbr.json
OpenDiscovery-2.5.dist-info/top_level.txt
