Metadata-Version: 2.0
Name: OpenDiscovery
Version: 2.5
Summary: Computational Drug Discovery Software
Home-page: https://github.com/iamgp/OpenDiscovery
Author: Gareth Price
Author-email: gareth.price@warwick.ac.uk
License: GPL
Keywords: OpenDiscovery
Platform: UNKNOWN
Classifier: Development Status :: 4 - Beta
Classifier: Intended Audience :: Developers
Classifier: Intended Audience :: Education
Classifier: Intended Audience :: Science/Research
Classifier: License :: OSI Approved :: GNU General Public License v3 (GPLv3)
Classifier: Natural Language :: English
Classifier: Programming Language :: Python :: 2.7
Classifier: Topic :: Scientific/Engineering :: Bio-Informatics
Classifier: Topic :: Scientific/Engineering :: Chemistry
Requires-Dist: argparse
Requires-Dist: docopt
Requires-Dist: matplotlib
Requires-Dist: numpy
Requires-Dist: pandas
Requires-Dist: termcolor
